word_embedder/__init__.py
word_embedder/get_vectors.py
word_embedder/embedders/__init__.py
word_embedder/embedders/base.py
word_embedder/embedders/keyed_vectors.py
word_embedder/embedders/keyed_vectors_light.py
word_embedder/embedders/keyed_vectors_on_disk.py
word_embedder/embedders/library.py
word_embedder/embedders/oov_error.py
word_embedder/embedders/utils.py
word_embedder/embedders/tests/__init__.py
word_embedder/embedders/tests/keyed_vectors_test_template.py
word_embedder/embedders/tests/test_keyed_vectors.py
word_embedder/embedders/tests/test_keyed_vectors_light.py
word_embedder/embedders/tests/test_keyed_vectors_on_disk.py
word_embedder/embedders/tests/test_low_memory_vec_loader.py
word_embedder/tests/__init__.py
word_embedder/tests/test_get_vectors.py
word_embedder-1.0.0.dist-info/LICENSE
word_embedder-1.0.0.dist-info/METADATA
word_embedder-1.0.0.dist-info/WHEEL
word_embedder-1.0.0.dist-info/top_level.txt
word_embedder-1.0.0.dist-info/RECORD
