Metadata-Version: 2.1
Name: word-embedder
Version: 1.0.0
Summary: Word Embedder
Home-page: UNKNOWN
Author: Solumilken
Author-email: UNKNOWN
License: MIT
Platform: UNKNOWN
Classifier: Programming Language :: Python
Classifier: Programming Language :: Python :: 3.6
Requires-Dist: mkdir-p (>=0.1.1)
Requires-Dist: numpy (>=1.15.1)
Requires-Dist: python-dotenv (==0.9.1)
